{
  "project_info": {
    "project_number": "165852388585",
    "project_id": "app-coffee-f13ab",
    "storage_bucket": "app-coffee-f13ab.appspot.com"
  },
  "client": [
    {
      "client_info": {
        "mobilesdk_app_id": "1:165852388585:android:c6d7bad678f67d45b1e478",
        "android_client_info": {
          "package_name": "com.example.flutter_application_2"
        }
      },
      "oauth_client": [],
      "api_key": [
        {
          "current_key": "AIzaSyD3X2WdwVTYoyMKC8xxOjEl0FDH1wTJ4CI"
        }
      ],
      "services": {
        "appinvite_service": {
          "other_platform_oauth_client": []
        }
      }
    }
  ],
  "configuration_version": "1"
}